setup.py
QitianSDK/__init__.py
QitianSDK/manager.py
QitianSDK.egg-info/PKG-INFO
QitianSDK.egg-info/SOURCES.txt
QitianSDK.egg-info/dependency_links.txt
QitianSDK.egg-info/requires.txt
QitianSDK.egg-info/top_level.txt