Metadata-Version: 2.1
Name: QitianSDK
Version: 0.2.2
Summary: 方便SmartDjango部署的齐天簿SDK
Home-page: https://github.com/Jyonn/QitianSDK
Author: Jyonn Liu
Author-email: i@6-79.cn
License: MIT Licence
Keywords: qitian,SmartDjango
Platform: any
Requires-Dist: smartdjango>=4.2.1
Requires-Dist: requests
Requires-Dist: oba
